<?xml version="1.0" ?>
<levels>
  <level id="1">
    <![CDATA[
 8       6\
   8   6 6\
 4     6  \
     4 8  \
 4 8 6    \
    ]]>
  </level>
  <level id="2">
    <![CDATA[
 8   6 6  \
   8     8\
         6\
 6 8 6    \
       4 6\
    ]]>
  </level>
  <level id="3">
    <![CDATA[
     6 8    \
   8   8   6\
       6    \
   8 8 6 6  \
     8      \
   6 6   6 6\
    ]]>
  </level>
  <level id="4">
    <![CDATA[
       6 4  \
 6   8     6\
 6   8     8\
   4     4  \
   8 8  10  \
       6 4  \
    ]]>
  </level>
  <level id="5">
    <![CDATA[
       8    \
 610   8 6 6\
 8 4        \
   8   6 8  \
           6\
   6 6     6\
    ]]>
  </level>
  <level id="6">
    <![CDATA[
    1210    \
 410        \
 4   4   4 4\
   6        \
10 6        \
     8   610\
    ]]>
  </level>
  <level id="7">
    <![CDATA[
   8   4    \
      10    \
   6       6\
            \
12 6  10 8 6\
    12   8 \
    ]]>
  </level>
  <level id="8">
    <![CDATA[
   6 8     8  \
   4    10 4  \
   8   8      \
      10      \
   6 4 8      \
10 8         8\
   6   4 6 8  \
    ]]>
  </level>
  <level id="9">
    <![CDATA[
 8         8  \
     6      10\
   8 4   8 8 4\
10     6      \
     4 4 6 6  \
   6     6 8  \
   4   8   6  \
    ]]>
  </level>
  <level id="10">
    <![CDATA[
  12     4    \
10   8        \
 8    12   6  \
        10  10\
           4 4\
 4   81012    \
   6 4        \
    ]]>
  </level>
  <level id="11">
    <![CDATA[
              \
   610     8 8\
12  10       8\
   6 6     6 8\
   8   6      \
       8     6\
10       6    \
    ]]>
  </level>
  <level id="12">
    <![CDATA[
    10     8 6\
         8 4  \
 4   8 4 8   6\
      10      \
   8   6     4\
    10 6      \
     8  10 6  \
    ]]>
  </level>
</levels>
